LICENSE
MANIFEST.in
README.rst
setup.cfg
setup.py
django_wms.egg-info/PKG-INFO
django_wms.egg-info/SOURCES.txt
django_wms.egg-info/dependency_links.txt
django_wms.egg-info/requires.txt
django_wms.egg-info/top_level.txt
wms/__init__.py
wms/layers.py
wms/maps.py
wms/models.py
wms/symbols.py
wms/views.py