Metadata-Version: 1.1
Name: django-wms
Version: 0.1.12
Summary: Mapscript based WMS framework for GeoDjango
Home-page: https://github.com/geodesign/django-wms
Author: Daniel Wiesmann
Author-email: daniel@urbmet.com
License: BSD
Keywords: django,gis,mapserver,mapscript,wms,tms,web map service,tile map service
Platform: UNKNOWN
Classifier: Development Status :: 3 - Alpha
Classifier: Environment :: Web Environment
Classifier: Framework :: Django
Classifier: Framework :: Django :: 1.9
Classifier: Intended Audience :: Developers
Classifier: License :: OSI Approved :: BSD License
Classifier: Operating System :: OS Independent
Classifier: Programming Language :: Python
Classifier: Programming Language :: Python :: 2
Classifier: Programming Language :: Python :: 2.7
Classifier: Topic :: Internet :: WWW/HTTP
Classifier: Topic :: Internet :: WWW/HTTP :: Dynamic Content
Classifier: Topic :: Scientific/Engineering :: GIS
